tmu/__init__.py
tmu/_cb.abi3.so
tmu/_tools.abi3.so
tmu/_wb.abi3.so
tmu/clause_bank.py
tmu/clause_bank_cuda.py
tmu/clause_bank_cuda_kernels.py
tmu/clause_bank_extension_build.py
tmu/clause_bank_numba.py
tmu/clause_bank_parallel.py
tmu/tools.py
tmu/tools_extension_build.py
tmu/tsetlin_machine.py
tmu/weight_bank.py
tmu/weight_bank_extension_build.py
tmu2-0.6.1.dist-info/LICENSE
tmu2-0.6.1.dist-info/METADATA
tmu2-0.6.1.dist-info/WHEEL
tmu2-0.6.1.dist-info/top_level.txt
tmu2-0.6.1.dist-info/RECORD
