Metadata-Version: 2.1
Name: tmu2
Version: 0.6.1
Summary: Implements the Tsetlin Machine, Coalesced Tsetlin Machine, Convolutional Tsetlin Machine, Regression Tsetlin Machine, and Weighted Tsetlin Machine, with support for continuous features, drop clause, Type III Feedback, focused negative sampling, multi-task classifier, autoencoder, literal budget, and one-vs-one multi-class classifier. TMU is written in Python with wrappers for C and CUDA-based clause evaluation and updating.
Home-page: https://github.com/cair/tmu/
Author: Ole-Christoffer Granmo
Author-email: ole.granmo@uia.no
License: MIT
Platform: UNKNOWN
License-File: LICENSE
Requires-Dist: cffi (>=1.0.0)
